monocle_slider/models.py
monocle_slider/monocle.py
monocle_slider/__init__.py
monocle_slider/admin.py
monocle_slider/templates/monocle_slider/monocle_slider.html
monocle_slider/fixtures/monocle_slider.json
monocle_slider/fixtures/monocle_slider/banner_2.jpg
monocle_slider/fixtures/monocle_slider/Penguins.jpg
monocle_slider/fixtures/monocle_slider/Desert.jpg
monocle_slider/fixtures/monocle_slider/Chrysanthemum.jpg
monocle_slider/fixtures/monocle_slider/banner_1.jpg
monocle_slider/fixtures/monocle_slider/banner_4.jpg
monocle_slider/fixtures/monocle_slider/banner_3.jpg
monocle_slider/fixtures/monocle_slider/Koala.jpg
monocle_slider/static/monocle_slider/monocle_slider.css
monocle_slider/static/monocle_slider/monocle_slider.js
monocle_slider-0.1.4.dist-info/RECORD
monocle_slider-0.1.4.dist-info/top_level.txt
monocle_slider-0.1.4.dist-info/DESCRIPTION.rst
monocle_slider-0.1.4.dist-info/METADATA
monocle_slider-0.1.4.dist-info/metadata.json
monocle_slider-0.1.4.dist-info/WHEEL
